sigmt/__init__.py
sigmt/__version__.py
sigmt/main.py
sigmt/core/band_averaging.py
sigmt/core/data_selection_tools.py
sigmt/core/perform_data_selection.py
sigmt/core/plots.py
sigmt/core/robust_estimation.py
sigmt/core/sigproc.py
sigmt/core/statistics.py
sigmt/gui/__init__.py
sigmt/gui/about_dialog.py
sigmt/gui/edi_merger.py
sigmt/gui/metronix.py
sigmt/gui/metronix_dialogs.py
sigmt/gui/project_related/create_project.py
sigmt/gui/project_related/edit_project.py
sigmt/images/sigmt.ico
sigmt/utils/__init__.py
sigmt/utils/frequency_table.py
sigmt/utils/utils.py
sigmt/utils/edi/edi_ops.py
sigmt/utils/metronix/cal_from_metronix_txt.py
sigmt/utils/metronix/cal_from_xml.py
sigmt/utils/metronix/calibration.py
sigmt/utils/metronix/metronix_utils.py
sigmt-2.1.3.dist-info/LICENSE
sigmt-2.1.3.dist-info/METADATA
sigmt-2.1.3.dist-info/WHEEL
sigmt-2.1.3.dist-info/entry_points.txt
sigmt-2.1.3.dist-info/top_level.txt
sigmt-2.1.3.dist-info/RECORD
