Metadata-Version: 2.1
Name: sigmt
Version: 2.1.3
Summary: A tool for magnetotelluric time series processing
Home-page: https://github.com/ajithabhks/sigmt
Author: Ajithabh K.S.
Author-email: ajithabhks@gmail.com
License: GPL
Classifier: License :: OSI Approved :: GNU General Public License (GPL)
Classifier: Programming Language :: Python :: 3
Classifier: Development Status :: 4 - Beta
Requires-Python: >=3.8
License-File: LICENSE
Requires-Dist: h5py
Requires-Dist: matplotlib
Requires-Dist: numpy
Requires-Dist: pandas
Requires-Dist: pyyaml
Requires-Dist: PyQt5
Requires-Dist: scikit-learn
Requires-Dist: scipy
Requires-Dist: seaborn
Requires-Dist: setuptools>=64.0.0
Requires-Dist: xarray
